traycortex/__init__.py
traycortex/borgmatic.py
traycortex/client.py
traycortex/config.py
traycortex/defaults.py
traycortex/images/borgmatic.png
traycortex/images/borgmatic_i.png
traycortex/images/borgmatic_i_r.png
traycortex/images/borgmatic_r.png
traycortex/log.py
traycortex/tray.py
traycortex-0.5.1.dist-info/LICENSE
traycortex-0.5.1.dist-info/METADATA
traycortex-0.5.1.dist-info/WHEEL
traycortex-0.5.1.dist-info/entry_points.txt
traycortex-0.5.1.dist-info/RECORD
