Metadata-Version: 2.1
Name: traycortex
Version: 0.5.1
Summary: borgmatic systray icon
License: GPL-3.0-only
Author: Sebastian Stark
Author-email: sstark@mailbox.org
Requires-Python: >=3.9,<4.0
Classifier: License :: OSI Approved :: GNU General Public License v3 (GPLv3)
Classifier: Programming Language :: Python :: 3
Classifier: Programming Language :: Python :: 3.9
Classifier: Programming Language :: Python :: 3.10
Classifier: Programming Language :: Python :: 3.11
Classifier: Programming Language :: Python :: 3.12
Requires-Dist: pillow (>=10.3.0,<11.0.0)
Requires-Dist: platformdirs (>=4.2.2,<5.0.0)
Requires-Dist: pygobject (>=3.48.2,<4.0.0)
Requires-Dist: pystray (>=0.19.5,<0.20.0)
